exv.py
version.py
xlfile.py
exv-1.3.dist-info/LICENSE
exv-1.3.dist-info/METADATA
exv-1.3.dist-info/WHEEL
exv-1.3.dist-info/entry_points.txt
exv-1.3.dist-info/top_level.txt
exv-1.3.dist-info/RECORD
