Metadata-Version: 2.1
Name: exv
Version: 1.3
Summary: View Excel files in the terminal
Author-email: Lars Arvestad <arve@math.su.se>
License: GNU General Public License v3 (GPLv3)
Project-URL: homepage, http://github.com/arvestad/exv
Classifier: Programming Language :: Python :: 3
Classifier: License :: OSI Approved :: GNU General Public License v3 (GPLv3)
Classifier: Operating System :: OS Independent
License-File: LICENSE
Requires-Dist: tabulate
Requires-Dist: openpyxl >3.0
Requires-Dist: xlrd >2.0
Requires-Dist: odsparsator >1.1
